habitat_sim/__init__.py
habitat_sim/attributes.py
habitat_sim/attributes_managers.py
habitat_sim/errors.py
habitat_sim/geo.py
habitat_sim/gfx.py
habitat_sim/logging.py
habitat_sim/metadata.py
habitat_sim/physics.py
habitat_sim/registry.py
habitat_sim/scene.py
habitat_sim/sensor.py
habitat_sim/sim.py
habitat_sim/simulator.py
habitat_sim/agent/__init__.py
habitat_sim/agent/agent.py
habitat_sim/agent/controls/__init__.py
habitat_sim/agent/controls/controls.py
habitat_sim/agent/controls/default_controls.py
habitat_sim/agent/controls/object_controls.py
habitat_sim/agent/controls/pyrobot_noisy_controls.py
habitat_sim/bindings/__init__.py
habitat_sim/nav/__init__.py
habitat_sim/nav/greedy_geodesic_follower.py
habitat_sim/robots/__init__.py
habitat_sim/robots/fetch_robot.py
habitat_sim/robots/mobile_manipulator.py
habitat_sim/robots/robot_interface.py
habitat_sim/sensors/__init__.py
habitat_sim/sensors/sensor_suite.py
habitat_sim/sensors/noise_models/__init__.py
habitat_sim/sensors/noise_models/gaussian_noise_model.py
habitat_sim/sensors/noise_models/no_noise_model.py
habitat_sim/sensors/noise_models/poisson_noise_model.py
habitat_sim/sensors/noise_models/redwood_depth_noise_model.py
habitat_sim/sensors/noise_models/salt_and_pepper_noise_model.py
habitat_sim/sensors/noise_models/sensor_noise_model.py
habitat_sim/sensors/noise_models/speckle_noise_model.py
habitat_sim/sensors/noise_models/data/redwood-depth-dist-model.npy
habitat_sim/utils/__init__.py
habitat_sim/utils/collect_env.py
habitat_sim/utils/common.py
habitat_sim/utils/compare_profiles.py
habitat_sim/utils/datasets_download.py
habitat_sim/utils/gfx_replay_utils.py
habitat_sim/utils/manager_utils.py
habitat_sim/utils/profiling_utils.py
habitat_sim/utils/validators.py
habitat_sim/utils/viz_utils.py
habitat_sim/utils/data/__init__.py
habitat_sim/utils/data/data_extractor.py
habitat_sim/utils/data/data_structures.py
habitat_sim/utils/data/pose_extractor.py
habitat_sim_uv_wheels_experimental-0.2.2.dist-info/METADATA
habitat_sim_uv_wheels_experimental-0.2.2.dist-info/WHEEL
habitat_sim_uv_wheels_experimental-0.2.2.dist-info/top_level.txt
habitat_sim_uv_wheels_experimental-0.2.2.dist-info/RECORD
